djangocms_pai_vue_mdc_adapter/__init__.py
djangocms_pai_vue_mdc_adapter/apps.py
djangocms_pai_vue_mdc_adapter/templates/djangocms_pai_vue_mdc_adapter/base.html
djangocms_pai_vue_mdc_adapter-0.0.1.dist-info/AUTHORS.rst
djangocms_pai_vue_mdc_adapter-0.0.1.dist-info/LICENSE.txt
djangocms_pai_vue_mdc_adapter-0.0.1.dist-info/METADATA
djangocms_pai_vue_mdc_adapter-0.0.1.dist-info/WHEEL
djangocms_pai_vue_mdc_adapter-0.0.1.dist-info/top_level.txt
djangocms_pai_vue_mdc_adapter-0.0.1.dist-info/RECORD
