Metadata-Version: 2.1
Name: djangocms-pai-vue-mdc-adapter
Version: 0.0.1
Summary: Vue MDC Adapter template app
Home-page: https://bitbucket.org/pai/djangocms-pai-vue-mdc-adapter
Author: pai
Author-email: paiuolo@gmail.com
License: mit
Platform: any
Classifier: Development Status :: 4 - Beta
Classifier: Programming Language :: Python
Provides-Extra: testing
Requires-Dist: pytest ; extra == 'testing'
Requires-Dist: pytest-cov ; extra == 'testing'
